medilab/__init__.py
medilab/admin.py
medilab/apps.py
medilab/forms.py
medilab/models.py
medilab/urls.py
medilab/views.py
medilab/static/medilab/css/style.css
medilab/static/medilab/img/about.jpg
medilab/static/medilab/img/apple-touch-icon.png
medilab/static/medilab/img/departments-1.jpg
medilab/static/medilab/img/departments-2.jpg
medilab/static/medilab/img/departments-3.jpg
medilab/static/medilab/img/departments-4.jpg
medilab/static/medilab/img/departments-5.jpg
medilab/static/medilab/img/favicon.png
medilab/static/medilab/img/hero-bg.jpg
medilab/static/medilab/img/doctors/doctors-1.jpg
medilab/static/medilab/img/doctors/doctors-2.jpg
medilab/static/medilab/img/doctors/doctors-3.jpg
medilab/static/medilab/img/doctors/doctors-4.jpg
medilab/static/medilab/img/gallery/gallery-1.jpg
medilab/static/medilab/img/gallery/gallery-2.jpg
medilab/static/medilab/img/gallery/gallery-3.jpg
medilab/static/medilab/img/gallery/gallery-4.jpg
medilab/static/medilab/img/gallery/gallery-5.jpg
medilab/static/medilab/img/gallery/gallery-6.jpg
medilab/static/medilab/img/gallery/gallery-7.jpg
medilab/static/medilab/img/gallery/gallery-8.jpg
medilab/static/medilab/img/testimonials/testimonials-1.jpg
medilab/static/medilab/img/testimonials/testimonials-2.jpg
medilab/static/medilab/img/testimonials/testimonials-3.jpg
medilab/static/medilab/img/testimonials/testimonials-4.jpg
medilab/static/medilab/img/testimonials/testimonials-5.jpg
medilab/static/medilab/js/main.js
medilab/static/medilab/js/portfolio.js
medilab/static/medilab/js/portfolio_slider.js
medilab/static/medilab/scss/_footer.scss
medilab/static/medilab/scss/_general.scss
medilab/static/medilab/scss/_header.scss
medilab/static/medilab/scss/_hero.scss
medilab/static/medilab/scss/_nav.scss
medilab/static/medilab/scss/_sections.scss
medilab/static/medilab/scss/_variables.scss
medilab/static/medilab/scss/style.scss
medilab/static/medilab/vendor/animate.css/animate.compat.css
medilab/static/medilab/vendor/animate.css/animate.css
django_medilab_ds_mylifedc-0.8.5.dist-info/LICENSE
django_medilab_ds_mylifedc-0.8.5.dist-info/METADATA
django_medilab_ds_mylifedc-0.8.5.dist-info/WHEEL
django_medilab_ds_mylifedc-0.8.5.dist-info/top_level.txt
django_medilab_ds_mylifedc-0.8.5.dist-info/RECORD
